wspier/__init__.py
wspier/core.py
wspier/io.py
wspier/net.py
wspier/tester.py
wspier-0.10.24.post2.dist-info/LICENSE
wspier-0.10.24.post2.dist-info/METADATA
wspier-0.10.24.post2.dist-info/WHEEL
wspier-0.10.24.post2.dist-info/top_level.txt
wspier-0.10.24.post2.dist-info/RECORD
