Metadata-Version: 2.1
Name: wspier
Version: 0.10.24.post2
Summary: worsoon 4 python
Home-page: https://go.worsoon.com/fwlink/?linkid=14
Author: worsoon
Author-email: airego@qq.com
License: Mulan PSL v2
Keywords: pip,wspier,worsoon,log
Platform: any
License-File: LICENSE
